<Requerimiento xmlns:xsi="http://www.w3.org/2001/XMLSchema-instance" xmlns:xsd="http://www.w3.org/2001/XMLSchema"><InformacionAdicional><Campo id="1"><Descripcion>Comentario</Descripcion><Valor /></Campo><Campo id="2"><Descripcion>Orden De Venta Asociada</Descripcion><Valor>Orden de traslado #1504</Valor></Campo></InformacionAdicional><Codigo>06</Codigo><NumeroDocumento>000000448</NumeroDocumento><FechaEmision>27/04/2026</FechaEmision><FechaEmisionPais>27/04/2026 00:00:00</FechaEmisionPais><FechaEmisionFormatoPais>27/04/2026</FechaEmisionFormatoPais><TasaCambioPrincipal>0</TasaCambioPrincipal><TasaCambioAlternativa>0</TasaCambioAlternativa><ValorMinimoPrincipal>0</ValorMinimoPrincipal><ValorMinimoAlternativo>0</ValorMinimoAlternativo><CondicionVenta /><CodigoReferencia /><TotalSinImpuestos>0</TotalSinImpuestos><TotalConImpuestos>0</TotalConImpuestos><Retencion /><DetallesProceso /><CodigoPagoLocalizacionExtranjera xsi:nil="true" /><CodigoTipoRegimenFiscalExterior xsi:nil="true" /><CodigoPaisEfectuaPago xsi:nil="true" /><AplicaConvenioDobleTributacion>false</AplicaConvenioDobleTributacion><EsPagoExteriorSujetoRetencionNormaLegal>false</EsPagoExteriorSujetoRetencionNormaLegal><ValidarFP>true</ValidarFP><NoProcesable>false</NoProcesable><EstadoComprobante>Autorizado</EstadoComprobante><ImprimeComprobante>false</ImprimeComprobante><ClaveAcceso>2704202606179180228400120290010000004480000044816</ClaveAcceso><NumeroAutorizacion>2704202606179180228400120290010000004480000044816</NumeroAutorizacion><FechaAutorizacion>27/04/2026 9:19:19</FechaAutorizacion><FechaIN>27/04/2026 09:19:18</FechaIN><IdRequerimiento>263229116335575567</IdRequerimiento><IdReqAsociado>0</IdReqAsociado><ReprocesoManual>false</ReprocesoManual><CodigoEmisor>2138</CodigoEmisor><RucEmisor>1791802284001</RucEmisor><Establecimiento>029</Establecimiento><Punto>001</Punto><Ambiente>2</Ambiente><Version>1.1.0</Version><TotalTributos>0</TotalTributos><Cliente><IdCliente>151886</IdCliente><RazonSocial>SISTEMAS CONSTRULIVIANOS CIA. LTDA</RazonSocial><Direccion>Capitan Edmundo Chiriboga N47-34 y Jorge Paez</Direccion><TipoIdentificacion>04</TipoIdentificacion><NumeroIdentificacion>1791802284001</NumeroIdentificacion><TipoCliente>0</TipoCliente><Ubicacion /><email>sistemas@siconecuador.com</email><NombreComercial xsi:nil="true" /><NumeroContribuyenteEspecial xsi:nil="true" /><ContabilidadObligada xsi:nil="true" /><CodigoTipoSujetoRetenido xsi:nil="true" /><EsParteRelacionalConEmisor>false</EsParteRelacionalConEmisor><Telefono>0</Telefono><CodigoPaisTelefono>0</CodigoPaisTelefono></Cliente><Transporte><DireccionOrigen>SAN JACINTO DE YAGUACHI / VIA AL PAN SN Y SN, GUAYAQUIL</DireccionOrigen><FechaInicio>27/04/2026</FechaInicio><FechaFin>30/04/2026</FechaFin><Transportista><RazonSocial>ALEXANDER ALVAREZ</RazonSocial><TipoIdentificacion>05</TipoIdentificacion><NumeroIdentificacion>0951145119</NumeroIdentificacion><Ubicacion /><email /><Placa>GTX3101</Placa><NombreComercial xsi:nil="true" /><NumeroContribuyenteEspecial xsi:nil="true" /><ContabilidadObligada xsi:nil="true" /><CodigoTipoSujetoRetenido xsi:nil="true" /><EsParteRelacionalConEmisor>true</EsParteRelacionalConEmisor></Transportista><Destinos><Destino id="1"><Establecimiento>012</Establecimiento><DireccionDestino>AV. DE LAS AMERICAS SOLAR 63 Y MZ 5</DireccionDestino><Motivo>Traslado</Motivo><Ruta /><Destinatario><RazonSocial>SISTEMAS CONSTRULIVIANOS CIA. LTDA</RazonSocial><Direccion>Capitan Edmundo Chiriboga N47-34 y Jorge Paez</Direccion><TipoIdentificacion>04</TipoIdentificacion><NumeroIdentificacion>1791802284001</NumeroIdentificacion><Ubicacion /><email>sistemas@siconecuador.com</email><NombreComercial xsi:nil="true" /><NumeroContribuyenteEspecial xsi:nil="true" /><ContabilidadObligada xsi:nil="true" /><CodigoTipoSujetoRetenido xsi:nil="true" /><EsParteRelacionalConEmisor>false</EsParteRelacionalConEmisor><Telefono>0</Telefono><CodigoPaisTelefono>0</CodigoPaisTelefono></Destinatario><Detalles><Detalle id="1"><Cantidad>30000</Cantidad><Exonerar>false</Exonerar><Producto><TipoProducto /><Codigo>ANTO0025</Codigo><Descripcion>TORNILLO PA GYPSUM ST 6X1PG</Descripcion><UnidadMedida>Un</UnidadMedida><CineCenter>false</CineCenter></Producto></Detalle></Detalles></Destino></Destinos></Transporte><TipoEnvio /><DetalleExportacion /><Canal>ApiClientV5</Canal><TotalIsc>0</TotalIsc><TotalIgv>0</TotalIgv><Gravadas>0</Gravadas><TotalDetraccion>0</TotalDetraccion><Procesar>false</Procesar><Actividad /><ResolucionFiscal xsi:nil="true" /></Requerimiento>
